{"nodes": [{"id": "deal_edit", "label": "deal-edit.js", "file_type": "code", "source_file": "admin/public/js/deal-edit.js", "source_location": "L1"}, {"id": "deal_edit_loaddeal", "label": "loadDeal()", "file_type": "code", "source_file": "admin/public/js/deal-edit.js", "source_location": "L25"}, {"id": "deal_edit_savedealfield", "label": "saveDealField()", "file_type": "code", "source_file": "admin/public/js/deal-edit.js", "source_location": "L72"}, {"id": "deal_edit_deletedeal", "label": "deleteDeal()", "file_type": "code", "source_file": "admin/public/js/deal-edit.js", "source_location": "L82"}, {"id": "deal_edit_reloaddeal", "label": "reloadDeal()", "file_type": "code", "source_file": "admin/public/js/deal-edit.js", "source_location": "L102"}, {"id": "deal_edit_openquickcashflow", "label": "openQuickCashflow()", "file_type": "code", "source_file": "admin/public/js/deal-edit.js", "source_location": "L134"}, {"id": "deal_edit_closequickcashflow", "label": "closeQuickCashflow()", "file_type": "code", "source_file": "admin/public/js/deal-edit.js", "source_location": "L186"}, {"id": "deal_edit_setquickcashflowtype", "label": "setQuickCashflowType()", "file_type": "code", "source_file": "admin/public/js/deal-edit.js", "source_location": "L191"}, {"id": "deal_edit_populatequickcategories", "label": "populateQuickCategories()", "file_type": "code", "source_file": "admin/public/js/deal-edit.js", "source_location": "L217"}, {"id": "deal_edit_updatequickcostitems", "label": "updateQuickCostItems()", "file_type": "code", "source_file": "admin/public/js/deal-edit.js", "source_location": "L233"}, {"id": "deal_edit_submitquickcashflow", "label": "submitQuickCashflow()", "file_type": "code", "source_file": "admin/public/js/deal-edit.js", "source_location": "L251"}], "edges": [{"source": "deal_edit", "target": "deal_edit_loaddeal", "relation": "contains", "confidence": "EXTRACTED", "source_file": "admin/public/js/deal-edit.js", "source_location": "L25", "weight": 1.0}, {"source": "deal_edit", "target": "deal_edit_savedealfield", "relation": "contains", "confidence": "EXTRACTED", "source_file": "admin/public/js/deal-edit.js", "source_location": "L72", "weight": 1.0}, {"source": "deal_edit", "target": "deal_edit_deletedeal", "relation": "contains", "confidence": "EXTRACTED", "source_file": "admin/public/js/deal-edit.js", "source_location": "L82", "weight": 1.0}, {"source": "deal_edit", "target": "deal_edit_reloaddeal", "relation": "contains", "confidence": "EXTRACTED", "source_file": "admin/public/js/deal-edit.js", "source_location": "L102", "weight": 1.0}, {"source": "deal_edit", "target": "deal_edit_openquickcashflow", "relation": "contains", "confidence": "EXTRACTED", "source_file": "admin/public/js/deal-edit.js", "source_location": "L134", "weight": 1.0}, {"source": "deal_edit", "target": "deal_edit_closequickcashflow", "relation": "contains", "confidence": "EXTRACTED", "source_file": "admin/public/js/deal-edit.js", "source_location": "L186", "weight": 1.0}, {"source": "deal_edit", "target": "deal_edit_setquickcashflowtype", "relation": "contains", "confidence": "EXTRACTED", "source_file": "admin/public/js/deal-edit.js", "source_location": "L191", "weight": 1.0}, {"source": "deal_edit", "target": "deal_edit_populatequickcategories", "relation": "contains", "confidence": "EXTRACTED", "source_file": "admin/public/js/deal-edit.js", "source_location": "L217", "weight": 1.0}, {"source": "deal_edit", "target": "deal_edit_updatequickcostitems", "relation": "contains", "confidence": "EXTRACTED", "source_file": "admin/public/js/deal-edit.js", "source_location": "L233", "weight": 1.0}, {"source": "deal_edit", "target": "deal_edit_submitquickcashflow", "relation": "contains", "confidence": "EXTRACTED", "source_file": "admin/public/js/deal-edit.js", "source_location": "L251", "weight": 1.0}, {"source": "deal_edit_loaddeal", "target": "deal_edit_openquickcashflow", "relation": "calls", "confidence": "EXTRACTED", "source_file": "admin/public/js/deal-edit.js", "source_location": "L63", "weight": 1.0}, {"source": "deal_edit_openquickcashflow", "target": "deal_edit_populatequickcategories", "relation": "calls", "confidence": "EXTRACTED", "source_file": "admin/public/js/deal-edit.js", "source_location": "L144", "weight": 1.0}, {"source": "deal_edit_openquickcashflow", "target": "deal_edit_setquickcashflowtype", "relation": "calls", "confidence": "EXTRACTED", "source_file": "admin/public/js/deal-edit.js", "source_location": "L160", "weight": 1.0}, {"source": "deal_edit_openquickcashflow", "target": "deal_edit_updatequickcostitems", "relation": "calls", "confidence": "EXTRACTED", "source_file": "admin/public/js/deal-edit.js", "source_location": "L166", "weight": 1.0}, {"source": "deal_edit_submitquickcashflow", "target": "deal_edit_closequickcashflow", "relation": "calls", "confidence": "EXTRACTED", "source_file": "admin/public/js/deal-edit.js", "source_location": "L300", "weight": 1.0}, {"source": "deal_edit_submitquickcashflow", "target": "deal_edit_reloaddeal", "relation": "calls", "confidence": "EXTRACTED", "source_file": "admin/public/js/deal-edit.js", "source_location": "L303", "weight": 1.0}]}